<?xml version="1.0" encoding="Windows-1251"?>
<questestinterop><item ident="QUE119"><presentation><material><mattext>Как создать событие в определенном календаре?</mattext></material><response_lid ident="LID119" rcardinality="Single"><render_choice><response_label ident="ANS10997"><material><mattext>Перед  добавлением события отключить все другие календари</mattext></material></response_label><response_label ident="ANS10998"><material><mattext>Указать данный календарь как календарь для приглашений</mattext></material></response_label><response_label ident="ANS10999"><material><mattext>Выбрать календарь в форме добавления события</mattext></material></response_label><response_label ident="ANS11000"><material><mattext>Никак</mattext></material></response_label></render_choice></response_lid></presentation><resprocessing><respcondition><conditionvar><varequal respident="LID119">ANS10999</varequal></conditionvar><setvar>10</setvar></respcondition></resprocessing><bitrix><description></description><description_type>text</description_type><incorrect_message></incorrect_message><self>N</self><sort>500</sort><active>Y</active></bitrix></item></questestinterop>